{
  "episodeId": "AI-CROSS-004",
  "estimatedSeconds": 270,
  "turns": [
    {
      "speaker": "面试官",
      "line": "AI 产品的指标对齐一直是个痛点，算法追求准确率，业务追求转化率。能否结合你负责过的一个真实项目，聊聊你是怎么在两个看似对立的指标体系之间求得共识的？"
    },
    {
      "speaker": "面试者",
      "line": "我曾负责过智能客服助理改版。当时核心冲突是：算法团队拿着离线测试集 95% 的准确率坚持要全量上线，但业务方拿着 Q2 灰度数据直接驳回，指出用户满意度评分从 4.2 骤降到 3.2，算法和业务两边互不妥协。"
    },
    {
      "speaker": "面试官",
      "line": "离线 95% 和满意度 3.2 的反差确实很大。你作为产品，是怎么切入并找到背后真实原因的？"
    },
    {
      "speaker": "面试者",
      "line": "我拉了 Q2 灰度期 1 万条用户会话日志，做了一次定量漏斗和定性会话回放。发现根本原因不在模型准确率本身，而在于‘首包响应时间’：模型计算完整回答需要 3.5 秒，导致前端白屏长达 3 秒，用户失去心智耐心直接点击了‘转人工’。"
    },
    {
      "speaker": "面试官",
      "line": "既然瓶颈在响应速度，那要提升速度势必需要算法做模型剪枝，这会直接降低准确率。当时算法团队愿意配合吗？"
    },
    {
      "speaker": "面试者",
      "line": "不愿意。算法认为准确率一旦跌破 92% 的行业红线，模型就失去了意义。而当时团队只给了一周排期。我们面临的限制是：要么花 1 个月做昂快的算力服务器扩容，要么在 7 天内通过非模型改动来解决等待焦虑。"
    },
    {
      "speaker": "面试官",
      "line": "那在一周的极限排期下，你最后做出了什么取舍来推进这个项目？"
    },
    {
      "speaker": "面试者",
      "line": "我们做了一个前端工程层面的妥协：后端模型不改，但开启流式输出（Streaming），在前端用打字机效果做平滑渲染。这样首包响应时间（TTFT）从 3.5 秒降到了 0.4 秒，虽然完整生成依然需要 3 秒，但用户的‘感知等待时间’被缩短到了 1 秒以内，成功在不降低准确率的情况下缓释了用户焦虑。"
    },
    {
      "speaker": "面试官",
      "line": "听起来是一个很巧妙的设计。但流式渲染加上复杂的客服网络环境，上线后有没有遇到过一些未曾预料的边界翻车？"
    },
    {
      "speaker": "面试者",
      "line": "确实翻车了。在 3G 等弱网环境下，流式传输经常因为网络抖动出现长达 2 秒的停顿，用户以为 AI 宕机了，灰度前 3 天转接人工的概率反而增加了 15%。我们赶紧复盘，增加了‘前端平滑输出队列防抖’以及‘网络超时 3 秒自动回退至渐进气泡提示’的容错兜底机制。"
    },
    {
      "speaker": "面试官",
      "line": "从准确率和满意度的指标冲突，到首包响应瓶颈的定量定位，再到 7 天排期下的流式打字机折中方案，以及弱网防抖的边界复盘。你不仅给出了框架，还通过真实的交互与工程细节证明了落地的可行性，回答非常扎实。"
    }
  ]
}