{
  "episodeId": "UX-005",
  "estimatedSeconds": 210,
  "turns": [
    {
      "speaker": "面试官",
      "line": "讲一个你推翻过初始需求的项目吧，为什么推、怎么说服对方的？"
    },
    {
      "speaker": "面试者",
      "line": "内容 App 的 PM 提了一个需求——首页增加显眼的打赏按钮，说能帮创作者变现。我看了数据发现 80% 的打赏发生在阅读超过 3 分钟的用户身上，首页打赏按钮的点击率几乎是零。"
    },
    {
      "speaker": "面试官",
      "line": "那你的判断是什么？打赏功能本身有问题还是位置错了？"
    },
    {
      "speaker": "面试者",
      "line": "需求没问题，场景错了。用户需要先跟内容建立情感连接才会打赏，在首页还没看内容就让人掏钱，逻辑上就不通。真正的痛点在文末，打赏链路藏得太深，要跳转三步才能完成。"
    },
    {
      "speaker": "面试官",
      "line": "你怎么说服 PM 放弃他的方案？他可能觉得曝光量大就是好事。"
    },
    {
      "speaker": "面试者",
      "line": "我没直接说不行。我把两种方案都做了高保真原型，找了 8 个用户做可用性测试。首页按钮组用户反馈“像乞讨”，文末方案的自然融入度评分 4.2/5。PM 看完视频回放自己就改了主意。"
    },
    {
      "speaker": "面试官",
      "line": "用户测试视频比报告更有说服力。最终方案效果怎么样？"
    },
    {
      "speaker": "面试者",
      "line": "文末打赏入口上线后，打赏转化率从 0.3% 升到 2.1%，创作者收入翻了三倍。首页没有增加任何干扰，阅读完成率还微涨了。后来这个模式推广到了全站所有内容详情页。"
    },
    {
      "speaker": "面试官",
      "line": "用数据验证代替意见分歧，这个做法展示了你的设计判断力。"
    }
  ]
}
