{
  "episodeId": "UX-003",
  "estimatedSeconds": 210,
  "turns": [
    {
      "speaker": "面试官",
      "line": "聊一个具体的：你遇到过最难的设计取舍是什么，最后怎么决定的？"
    },
    {
      "speaker": "面试者",
      "line": "去年做内容社区 App 的信息架构改版，用户研究显示新用户觉得首页太乱找不到入口，但老用户抱怨改版后常用功能藏深了。"
    },
    {
      "speaker": "面试官",
      "line": "这确实是典型的两难。你的判断标准是什么？"
    },
    {
      "speaker": "面试者",
      "line": "我定了三条原则：一保核心任务效率不动，二新增用户引导但不影响老用户肌肉记忆，三用数据验证而不是拍脑袋。"
    },
    {
      "speaker": "面试官",
      "line": "听起来合理。但你具体怎么平衡两类用户的需求？"
    },
    {
      "speaker": "面试者",
      "line": "我做了一个分层方案：首页首屏保留老用户最高频的 4 个入口完全不变，把新增的探索模块放在第二屏。新用户首次进入时有一个轻量的 overlay 引导，看一次后自动消失。"
    },
    {
      "speaker": "面试官",
      "line": "这个 overlay 不会把新用户的体验搞得更复杂吗？"
    },
    {
      "speaker": "面试者",
      "line": "会，所以我们在 overlay 上线前用原型做了 5 人可用性测试。结果发现新用户在没有引导的情况下平均需要 47 秒才能找到发布入口，有引导后降到 12 秒。我们才决定上线。"
    },
    {
      "speaker": "面试官",
      "line": "灰度数据验证了两边兼顾的可能性，这个取舍思路清晰。回答展示了你的数据决策力。"
    },
    {
      "speaker": "面试者",
      "line": "灰度两周，新用户次日留存提升 6%，老用户活跃度和核心操作路径没有统计显著变化。这个结果说明分层方案基本做到了两边的平衡。"
    }
  ]
}